qparameterize/__init__.py
qparameterize/main.py
qparameterize/qparameterize.py
qparameterize-0.1.1.dist-info/METADATA
qparameterize-0.1.1.dist-info/WHEEL
qparameterize-0.1.1.dist-info/entry_points.txt
qparameterize-0.1.1.dist-info/licenses/LICENSE
qparameterize-0.1.1.dist-info/RECORD
