Metadata-Version: 2.4
Name: qparameterize
Version: 0.1.1
Summary: Parameterise a Quarto document for the Jupyter Engine
Project-URL: Issues, https://github.com/has2k1/qparameterize/issues
Project-URL: Source, https://github.com/has2k1/qparameterize
Author-email: Hassan Kibirige <has2k1@gmail.com>
License-Expression: MIT
License-File: LICENSE
Keywords: quarto
Requires-Python: >=3.11
Requires-Dist: pyyaml>=6.0
